k1rh4pip/__init__.py
k1rh4pip/test.py
k1rh4pip-0.3.dist-info/DESCRIPTION.rst
k1rh4pip-0.3.dist-info/METADATA
k1rh4pip-0.3.dist-info/RECORD
k1rh4pip-0.3.dist-info/WHEEL
k1rh4pip-0.3.dist-info/metadata.json
k1rh4pip-0.3.dist-info/top_level.txt
