Metadata-Version: 2.0
Name: k1rh4pip
Version: 0.3
Summary: k1rh4 pip test
Home-page: https://github.com/k1rh4/k1rh4pip
Author: k1rh4.lee
Author-email: k1rha87@gmail.com
License: UNKNOWN
Download-URL: https://github.com/k1rh4/k1rh4pip/archive/master.zip
Keywords: pypi k2rh4
Platform: UNKNOWN
Classifier: Programming Language :: Python :: 3
Classifier: Programming Language :: Python :: 3.2
Classifier: Programming Language :: Python :: 3.3
Classifier: Programming Language :: Python :: 3.4
Classifier: Programming Language :: Python :: 3.5
Classifier: Programming Language :: Python :: 3.6
Classifier: Programming Language :: Python :: 3.7
Requires-Python: >=3
